{
  "name": "Hilda Dean",
  "age": 23,
  "address": {
    "street": "Ozba Loop",
    "city": "Ifadeniv",
    "state": "KS",
    "zip": "41527"
  },
  "contact": {
    "phone": "(341) 803-5265",
    "servicePhone": "800962436"
  },
  "birthday": "1966-05-10T11:59:00.864Z",
  "ip": "124.193.169.231",
  "foo": "bar",
  "profile": {
    "about": "Dog nausto cam hew wapmipwa onhel fetkufod satru ho ranla ihagfih izedu bow waakza. Ica omahe vuliris ba fufu ru karim cowudo tu zoppuvnom heisearo kevgok aj heeru. Omu julho gecpewaz et falec budaihe uwa vulecfa ipbavwer ge jioc ucifo ujuze puam hatujol uwu emi. Sanvuve ofgifmip apevug enohovaf ege febuhug heamrij cinzec jozrogo mijfefbu niorkoh zur osoleseji.",
    "bio": "Porawo uz zic nivbeduj depwakdo bekji dizis gulsav jilzov ale huka sud guzamuf ano igzabnos gega. Dobov giewowa hutuco vif jibob im koupoze odzas hazezees arewuni lum nidobu kutcimaw jiwapev du jor banlap hajmur. Pijibsi hivac espu pisnic gimwa ejwah keop vularbap ihudic galo boze opsec uhnovobi. Vebcone ovo fafcuud nug pe ewova zekwojnu bab hejroel iz bipmilo izemari lean jigmes ji. Lobtu nitter gibed rusga fi zengiuw geto narusna liuku pif eca zulhilav helu remagu pu."
  },
  "apiKey": "e3b27f735ea3bfd7ecc81d3552aa98eeaed898a148c507a49436effe8e8a91d3",
  "currency": {
    "code": "ARS",
    "name": "Argentina Peso"
  }
}