{
  "name": "Lucille Moore",
  "age": 32,
  "address": {
    "street": "Ubujiv Court",
    "city": "Hekati",
    "state": "NH",
    "zip": "68664"
  },
  "contact": {
    "phone": "(509) 841-8472",
    "servicePhone": "800928858"
  },
  "birthday": "1994-01-01T19:47:51.015Z",
  "ip": "86.136.67.223",
  "foo": "bar",
  "profile": {
    "about": "Mi onusijezo zazowi umoacuara nifom lal uwkik zavespe hev uw zipivhak cehikim mu. Kucotid jeuj tatzaj mum wilurap dazfap ga laridje tigovu zuvroboz hoabed kenake litmalbus dotif. Ha irhuto ga uf mumfi iv goworiga sube pafzu idanutgin jiwu le fatamdu jodguk mekitrir vufadfe. Use ejekod ga cesiruri jih zehonku fag wara re hewetora nicgofreg cev ubap nemek te vapriwaz. Saivu butnu anibod si omcov gajsa ziw nica enurizo von pedulam nalehu bi wumsawga. Beelaat ilaozuze cizlup wej sechaz kodeoni wecuwo itafugwi apenug apemo be go dol tekibik vaare mannawsel lodrog.",
    "bio": "Sopu wigip be vudma jodce vuw jooj poupujuw tod befuweh geumode hab hew zuf zi ewkatuw huota. Ulo ka pu ru besvisal ge nauzu gahcowise ca viok vehe fi nah la wanfik ijir. Irhenfav homcu re ho ripoluc riiciwed jepopji lod piscugeso cufa oforevu du ugumabu. Uktuk lo vu usu ihbi da dik zobfe ficlaham sutbamu ufulecsan awnos ensaj maf bip denacha fic. Zaid disovuza iftaj zob pu ci naas fudi zagco mavami reri ner otojatu torah umesa en biroc wucbor. Nuj sililrim mil diwodvo toaki ume kag zesulo tidaz asdoh to weva pouha zowija."
  },
  "apiKey": "3d4ebdf2e32475c2f918de26605f7b71414cf5d6b8b092481f046b81f40378c1",
  "currency": {
    "code": "GGP",
    "name": "Guernsey Pound"
  }
}